adv_data_processing/__init__.py
adv_data_processing/batch_processing.py
adv_data_processing/cleaning.py
adv_data_processing/config.py
adv_data_processing/data_preprocessing.py
adv_data_processing/data_transformation.py
adv_data_processing/data_validation.py
adv_data_processing/dimensionality_reduction.py
adv_data_processing/entity_recognition.py
adv_data_processing/error_handling.py
adv_data_processing/feature_engineering.py
adv_data_processing/feature_selection.py
adv_data_processing/imbalanced_data.py
adv_data_processing/loading.py
adv_data_processing/logging_setup.py
adv_data_processing/main.py
adv_data_processing/metrics.py
adv_data_processing/model_evaluation.py
adv_data_processing/monitoring.py
adv_data_processing/optimization.py
adv_data_processing/pipeline.py
adv_data_processing/setup.py
adv_data_processing/test_data_pipeline.py
adv_data_processing/text_analytics.py
adv_data_processing/topic_modeling.py
adv_data_processing/transformation.py
adv_data_processing/utils.py
adv_data_processing/validation.py
adv_data_processing/visualization.py
advanced_data_processing-0.2.7.dist-info/LICENSE
advanced_data_processing-0.2.7.dist-info/METADATA
advanced_data_processing-0.2.7.dist-info/WHEEL
advanced_data_processing-0.2.7.dist-info/top_level.txt
advanced_data_processing-0.2.7.dist-info/RECORD
