Metadata-Version: 2.1
Name: advanced-data-processing
Version: 0.2.7
Summary: An advanced data processing pipeline for machine learning workflows
Home-page: https://github.com/stochastic-sisyphus/adv_data_processing_pipeline
Author: Vanessa Beck
Author-email: your.email@example.com
License: MIT
Classifier: Development Status :: 4 - Beta
Classifier: Intended Audience :: Developers
Classifier: Intended Audience :: Science/Research
Classifier: License :: OSI Approved :: MIT License
Classifier: Programming Language :: Python :: 3
Classifier: Programming Language :: Python :: 3.8
Classifier: Programming Language :: Python :: 3.9
Classifier: Programming Language :: Python :: 3.10
Classifier: Programming Language :: Python :: 3.11
Classifier: Programming Language :: Python :: 3.12
Classifier: Topic :: Scientific/Engineering :: Artificial Intelligence
Classifier: Topic :: Software Development :: Libraries :: Python Modules
Requires-Python: >=3.8,<3.13
License-File: LICENSE
Requires-Dist: pandas>=1.5.0
Requires-Dist: dask[complete]>=2023.1.0
Requires-Dist: scikit-learn>=1.0.0
Requires-Dist: numpy>=1.23.0
Requires-Dist: beautifulsoup4>=4.11.0
Requires-Dist: pyyaml>=6.0.0
Requires-Dist: tenacity>=8.0.0
Requires-Dist: joblib>=1.2.0
Requires-Dist: tqdm>=4.65.0
Requires-Dist: schema>=0.7.5
Requires-Dist: sqlalchemy>=1.4.0
Requires-Dist: boto3>=1.26.0
Requires-Dist: requests>=2.28.0
Requires-Dist: cerberus>=1.3.4
Requires-Dist: psutil>=5.9.0
Requires-Dist: torch>=2.1.0
Requires-Dist: optuna>=3.3.0
Requires-Dist: mlflow>=2.8.0
Provides-Extra: all
Requires-Dist: mlflow>=2.8.0; extra == "all"
Requires-Dist: optuna>=3.3.0; extra == "all"
Requires-Dist: shap>=0.43.0; extra == "all"
Requires-Dist: lime>=0.2.0; extra == "all"
Requires-Dist: fastapi>=0.100.0; extra == "all"
Requires-Dist: docker>=6.1.0; extra == "all"
Requires-Dist: great-expectations>=0.17.0; extra == "all"
Requires-Dist: kedro>=0.18.0; extra == "all"
Requires-Dist: wandb>=0.15.0; extra == "all"
Requires-Dist: ray>=2.7.0; extra == "all"
Provides-Extra: nlp
Requires-Dist: nltk>=3.6.0; extra == "nlp"
Requires-Dist: spacy>=3.1.0; extra == "nlp"
Requires-Dist: gensim>=4.1.0; extra == "nlp"
Provides-Extra: viz
Requires-Dist: matplotlib>=3.4.0; extra == "viz"
Requires-Dist: seaborn>=0.11.0; extra == "viz"
Requires-Dist: plotly>=5.1.0; extra == "viz"
Provides-Extra: ml
Requires-Dist: scikit-learn>=1.0.0; extra == "ml"
Requires-Dist: imbalanced-learn>=0.8.0; extra == "ml"
Requires-Dist: xgboost>=1.5.0; extra == "ml"
Requires-Dist: lightgbm>=3.3.0; extra == "ml"
